<?xml version="1.0" encoding="UTF-8" ?>
<XMLDB PATH="admin/report/coursesize" VERSION="20110813" COMMENT="XMLDB file for coursesize report"
    xmlns:xsi="http://www.w3.org/2001/XMLSchema-instance"
    xsi:noNamespaceSchemaLocation="../../../lib/xmldb/xmldb.xsd"
>
  <TABLES>
    <TABLE NAME="course_filessize" COMMENT="Info about how much disk space a couses files are taking up">
      <FIELDS>
        <FIELD NAME="id" TYPE="int" LENGTH="10" NOTNULL="true" UNSIGNED="true" SEQUENCE="true" ENUM="false" NEXT="courseid"/>
        <FIELD NAME="courseid" TYPE="int" LENGTH="10" NOTNULL="true" UNSIGNED="true" DEFAULT="0" SEQUENCE="false" ENUM="false" PREVIOUS="id" NEXT="timemodified"/>
        <FIELD NAME="timemodified" TYPE="int" LENGTH="10" NOTNULL="true" UNSIGNED="true" DEFAULT="0" SEQUENCE="false" ENUM="false" PREVIOUS="courseid" NEXT="filessize"/>
        <FIELD NAME="filessize" TYPE="int" LENGTH="10" NOTNULL="true" UNSIGNED="true" DEFAULT="0" SEQUENCE="false" ENUM="false" PREVIOUS="timemodified"/>
      </FIELDS>
      <KEYS>
        <KEY NAME="primary" TYPE="primary" FIELDS="id" />
      </KEYS>
      <INDEXES>
        <INDEX NAME="courseid" UNIQUE="true" FIELDS="courseid"/>
      </INDEXES>
    </TABLE>
  </TABLES>
</XMLDB>
